pandoc_pdf/__init__.py
pandoc_pdf/main.py
pandoc_pdf_utils/default_config/deeplists.tex
pandoc_pdf_utils/default_config/defaults.yml
pandoc_pdf_utils/default_config/header.tex
pandoc_pdf_utils/default_config/setting.yml
pandoc_pdf_utils/env.py
pandoc_pdf_utils/functions.py
pandoc_pdf-0.1.12.dist-info/entry_points.txt
pandoc_pdf-0.1.12.dist-info/LICENSE
pandoc_pdf-0.1.12.dist-info/WHEEL
pandoc_pdf-0.1.12.dist-info/METADATA
pandoc_pdf-0.1.12.dist-info/RECORD
