Metadata-Version: 2.1
Name: pandoc-pdf
Version: 0.1.12
Summary: Command to generate pdf easily with pandoc.
License: MIT
Author: rai
Requires-Python: >=3.10,<4.0
Classifier: License :: OSI Approved :: MIT License
Classifier: Programming Language :: Python :: 3
Classifier: Programming Language :: Python :: 3.10
Requires-Dist: PyYAML (>=6.0,<7.0)
Requires-Dist: click (>=8.1.3,<9.0.0)
